CHANGELOG
INSTALL
LICENSE
MANIFEST.in
README
setup.cfg
setup.py
startfms.py
docs/en/html/.buildinfo
docs/en/html/config.html
docs/en/html/genindex.html
docs/en/html/index.html
docs/en/html/install.html
docs/en/html/objects.inv
docs/en/html/search.html
docs/en/html/searchindex.js
docs/en/html/startfms.html
docs/en/html/tutorial.html
docs/en/html/_sources/config.txt
docs/en/html/_sources/index.txt
docs/en/html/_sources/install.txt
docs/en/html/_sources/startfms.txt
docs/en/html/_sources/tutorial.txt
docs/en/html/_static/ajax-loader.gif
docs/en/html/_static/bandeau1.jpg
docs/en/html/_static/basic.css
docs/en/html/_static/comment-bright.png
docs/en/html/_static/comment-close.png
docs/en/html/_static/comment.png
docs/en/html/_static/default.css
docs/en/html/_static/doctools.js
docs/en/html/_static/down-pressed.png
docs/en/html/_static/down.png
docs/en/html/_static/favicon.ico
docs/en/html/_static/file.png
docs/en/html/_static/jcb.css
docs/en/html/_static/jquery.js
docs/en/html/_static/minus.png
docs/en/html/_static/plus.png
docs/en/html/_static/pygments.css
docs/en/html/_static/searchtools.js
docs/en/html/_static/sidebar.js
docs/en/html/_static/underscore.js
docs/en/html/_static/up-pressed.png
docs/en/html/_static/up.png
docs/en/html/_static/websupport.js
docs/en/man/experiment-conf.yml.5
docs/en/man/startfms.1
docs/examples/exp01.csv
docs/examples/exp01.log
docs/examples/exp01.yml
docs/examples/exp01b.csv
docs/examples/exp01b.yml
docs/examples/exp02.yml
docs/examples/exp03.log
docs/examples/exp03.yml
fms/__init__.py
fms/core.py
fms/version.py
fms.egg-info/PKG-INFO
fms.egg-info/SOURCES.txt
fms.egg-info/dependency_links.txt
fms.egg-info/requires.txt
fms.egg-info/top_level.txt
fms/agents/__init__.py
fms/agents/playorderlogfile.py
fms/agents/randomtrader.py
fms/agents/zerointelligencetrader.py
fms/engines/__init__.py
fms/engines/asynchronousrandwreplace.py
fms/engines/synchronousrandwreplace.py
fms/markets/__init__.py
fms/markets/continuousorderdriven.py
fms/markets/highestqtyfixing.py
fms/utils/__init__.py
fms/utils/exceptions.py
fms/utils/git.py
fms/utils/parsers.py
fms/worlds/__init__.py
