Metadata-Version: 1.0
Name: fms
Version: 0.1.9
Summary: A Financial Market Simulator
Home-page: http://github.com/jcbagneris/fms
Author: Jean-Charles Bagneris
Author-email: jcbagneris@gmail.com
License: BSD
Platform: UNKNOWN
Classifier: Development Status :: 4 - Beta
Classifier: Environment :: Console
Classifier: Intended Audience :: Science/Research
Classifier: License :: OSI Approved :: BSD License
Classifier: Operating System :: OS Independent
Classifier: Programming Language :: Python :: 2
Classifier: Topic :: Scientific/Engineering
